{
    "affinities": {
        "Alarm": {
            "Alarm Time Preference": "9:30 AM",
            "Alarm Sound Preference": "upbeat music",
            "Alarm Recurring Preference": "weekdays"
        },
        "Books": {
            "Genre": [
                "fantasy",
                "science-fiction",
                "young adult"
            ],
            "Favourite Authors": [
                "J.K. Rowling",
                "Philip Pullman",
                "Neil Gaiman"
            ],
            "Favourite Books": [
                "Harry Potter Series",
                "His Dark Materials",
                "The Graveyard Book"
            ],
            "Favourite Book Series": [
                "Harry Potter",
                "His Dark Materials"
            ],
            "Reading Format": [
                "ebook",
                "physical"
            ],
            "Reading Time Preference": [
                "evening"
            ],
            "Reading Frequency": "weekly"
        },
        "Buses": {
            "Preferred Bus Company": [
                "National Express",
                "Megabus"
            ],
            "Travel Frequency": [
                "weekly",
                "occasionally"
            ],
            "Seat Preference": "window",
            "Departure Time Preference": [
                "afternoon",
                "no preference"
            ]
        },
        "Calendar": {
            "Event Type Preference": [
                "social gatherings",
                "study sessions",
                "recreational activities"
            ],
            "Notification Preference": "30 minutes before",
            "Timezone": "UTC+0"
        },
        "Events": {
            "Event Type Preference": [
                "concerts",
                "comedy shows",
                "gaming conventions",
                "film screenings"
            ],
            "Price Range": [
                "under $50",
                "free"
            ],
            "Group Size Preference": "large group",
            "Seating Preference": [
                "general admission",
                "standing"
            ],
            "Days of Week Preference": "weekends"
        },
        "Finance": {
            "Preferred Sectors": [
                "technology",
                "consumer goods",
                "healthcare"
            ],
            "News Sources": [
                "financial news channels",
                "financial apps",
                "financial websites",
                "blogs"
            ],
            "Financial Company": [
                "Apple",
                "Amazon",
                "Netflix",
                "Tesla"
            ]
        },
        "Flights": {
            "Preferred Airline": [
                "RyanAir",
                "EasyJet",
                "Vueling"
            ],
            "Seat Class Preference": [
                "economy"
            ],
            "Layover Preference": [
                "non-stop",
                "short layover"
            ],
            "Seat Preference": "aisle",
            "Departure Time Preference": [
                "morning",
                "afternoon"
            ]
        },
        "Games": {
            "Preferred Game Genres": [
                "action",
                "RPG",
                "survival",
                "sandbox"
            ],
            "Gaming Platforms": [
                "PC",
                "PlayStation",
                "Nintendo Switch"
            ],
            "Multiplayer Preference": [
                "online multiplayer",
                "single player"
            ],
            "Gaming Frequency": [
                "daily",
                "2-3 hours per session"
            ],
            "Preferred Game Name": [
                "The Witcher 3: Wild Hunt",
                "Minecraft",
                "Red Dead Redemption 2"
            ]
        },
        "Hotels": {
            "Hotel Chains Preference": [
                "boutique",
                "budget"
            ],
            "Amenity Preference": [
                "free parking",
                "WiFi",
                "free breakfast",
                "gym"
            ],
            "Location Preference": [
                "city center",
                "near universities or colleges",
                "within walking distance of nightlife"
            ],
            "Star Rating Preference": [
                "3 star",
                "4 star"
            ],
            "Room Type Preference": [
                "double"
            ]
        },
        "Media": {
            "Preferred Genres": [
                "action",
                "comedy",
                "sci-fi",
                "adventure"
            ],
            "Favourite Actors and Directors": [
                "Tom Holland",
                "Chris Hemsworth",
                "Taika Waititi",
                "James Gunn"
            ],
            "Favourite Media": [
                "Spider-Man: No Way Home",
                "Thor: Ragnarok",
                "The Guardians of the Galaxy",
                "The Suicide Squad"
            ],
            "Viewing Platform Preference": [
                "Netflix",
                "Disney+",
                "Amazon Prime"
            ]
        },
        "Messaging": {
            "Preferred Messaging Apps": [
                "WhatsApp",
                "Snapchat",
                "Discord"
            ],
            "Communication Style": "text",
            "Frequent Contact": [
                "friends",
                "classmates"
            ],
            "Preferred Communication Style": "casual"
        },
        "Movies": {
            "Preferred Genres": [
                "action",
                "comedy",
                "science-fiction"
            ],
            "Favorite Actors and Directors": [
                "Tom Holland",
                "Chris Hemsworth",
                "Robert Downey Jr.",
                "Taika Waititi"
            ],
            "Theater Type Preference": [
                "IMAX",
                "standard"
            ],
            "Viewing Time Preference": [
                "late night",
                "weekends only",
                "during vacations"
            ],
            "Seat Type Preference": [
                "back row",
                "double seat"
            ]
        },
        "Music": {
            "Preferred Genres": [
                "rock",
                "punk",
                "hip-hop"
            ],
            "Favorite Artists": [
                "Arctic Monkeys",
                "Stormzy",
                "Dave"
            ],
            "Favorite Bands": [
                "Oasis",
                "The Clash",
                "Blink-182"
            ],
            "Favorite Albums": [
                "Whatever People Say I Am, That's What I'm Not",
                "Heavy Is the Head",
                "Enema of the State"
            ],
            "Platform Preference": [
                "Spotify",
                "YouTube Music",
                "SoundCloud"
            ],
            "Preferred Audio Quality": "standard",
            "Playlist Preference": [
                "Workout Playlists",
                "Discover Weekly",
                "Release Radar"
            ]
        },
        "Rental Cars": {
            "Car Type Preference": [
                "compact",
                "economy"
            ],
            "Preferred Rental Company": [
                "Zipcar",
                "Enterprise"
            ],
            "Preferred Car Brand": [
                "Volkswagen",
                "Honda",
                "Toyota"
            ],
            "Rental Duration Preference": "1-2 weeks",
            "Additional Feature Preference": [
                "GPS",
                "additional driver"
            ],
            "Preferred Fuel Type": "gasoline"
        },
        "Restaurants": {
            "Cuisine Preference": [
                "Mexican",
                "Thai",
                "Indian"
            ],
            "Dietary Restrictions": [
                "vegetarian"
            ],
            "Ambiance Preference": [
                "casual",
                "outdoor seating"
            ],
            "Price Range": [
                "budget-friendly",
                "moderate"
            ]
        },
        "Services": {
            "Preferred Service Provider Types": "budget",
            "Appointment Time Preference": [
                "evening"
            ],
            "Location Preference": [
                "near university",
                "within walking distance"
            ],
            "Service Frequency Preference": [
                "monthly",
                "one-off"
            ],
            "Service Provider Gender Preference": "no preference"
        },
        "Shopping": {
            "Preferred Product Category": [
                "electronics",
                "books",
                "musical instruments"
            ],
            "Price Range Preference": "budget",
            "Brand Preference": [
                "affordable",
                "well-reviewed",
                "environmentally conscious"
            ]
        },
        "Sports": {
            "Favorite Sports": [
                "soccer",
                "cricket",
                "rock climbing",
                "skateboarding"
            ],
            "Favorite Team": [
                "Manchester United FC",
                "England National Cricket Team"
            ],
            "Viewing Preference": "live"
        },
        "Train": {
            "Preferred Train Class": "standard class",
            "Travel Time Preference": [
                "evening",
                "morning"
            ],
            "Amenity Preference": [
                "WiFi",
                "power outlet"
            ],
            "Preferred Seat Type": "window"
        },
        "Travel": {
            "Preferred Destination Types": [
                "adventure",
                "city",
                "national park",
                "road trip"
            ],
            "Duration Preference": [
                "1-2 weeks",
                "3-4 weeks"
            ],
            "Group Size Preference": [
                "solo",
                "couple"
            ],
            "Frequent Travel Destination": [
                "Edinburgh",
                "London",
                "Amsterdam"
            ],
            "Travel Season Preference": [
                "Spring",
                "Summer"
            ]
        }
    },
    "demographics": {
        "user_id": "user853",
        "age": "18-24 years old",
        "gender": "Male",
        "employment_status": "Student",
        "education": "Some University but no degree",
        "marital_status": "Never been married",
        "english_proficiency": "Fluent",
        "ethnicity": "White",
        "religion": "Non-religious",
        "birth_country": "United Kingdom",
        "reside_country": "United Kingdom"
    },
    "interests": {
        "Alarm": 1,
        "Books": 1,
        "Buses": 1,
        "Calendar": 1,
        "Events": 1,
        "Finance": 0,
        "Flights": 0,
        "Games": 1,
        "Hotels": 0,
        "Media": 1,
        "Messaging": 1,
        "Movies": 1,
        "Music": 1,
        "Rental Cars": 0,
        "Restaurants": 1,
        "Services": 0,
        "Shopping": 1,
        "Sports": 1,
        "Train": 1,
        "Travel": 1
    },
    "interactions": {
        "Alarm": "The user, a young male student in his early 20s from the United Kingdom, frequently interacts with the alarm assistant to manage his daily schedule. As a university student with an irregular sleep pattern, he relies on the assistant to set recurring weekday alarms for 9:30 AM to ensure he doesn't oversleep for classes.\n\nInitially, the user preferred a standard alarm tone, but over time, he requested more upbeat and energetic music tracks to help him wake up feeling motivated. He often asks the assistant to suggest new, peppy songs to use as his alarm sound, showing an interest in exploring different genres like pop, rock, and electronic dance music.\n\nThe user appreciates the assistant's ability to set multiple alarms with varying tones, volumes, and snooze intervals, as he sometimes struggles to wake up on the first alarm. He has also requested the assistant to provide weather updates and reminders for important assignments or exams when setting his alarms.\n\nDuring exam periods or school breaks, the user adjusts his alarm preferences, either setting earlier or later wake-up times or disabling recurring alarms altogether. He values the flexibility to easily modify or cancel alarms based on his changing schedule.\n\nOver time, the user has developed a casual and friendly rapport with the assistant, often engaging in light-hearted banter or sharing anecdotes about his struggles with early morning classes. He appreciates the assistant's ability to understand context and provide personalized recommendations, such as suggesting earlier bedtimes or offering study tips alongside his alarm reminders.",
        "Books": "The user, an 18-24 year old male student from the United Kingdom, has a strong affinity for fantasy, science-fiction, and young adult literature. Past interactions with the virtual assistant have centered around exploring books within these genres, seeking recommendations, and discussing favorite authors and series.\n\nOne recurring theme has been the user's deep connection with the Harry Potter series by J.K. Rowling. They have frequently asked for insights into the books' themes, character development, and the author's writing process. The assistant has provided analyses, trivia, and fan theories, which the user has eagerly engaged with, often leading to lively discussions.\n\nAnother area of consistent interest has been the His Dark Materials trilogy by Philip Pullman. The user has requested recommendations for similar works that explore complex philosophical concepts and intricate world-building. In response, the assistant has suggested books by authors like Neil Gaiman, whose work \"The Graveyard Book\" has become a new favorite.\n\nOver time, the user's interactions have evolved from seeking basic plot summaries and character descriptions to more nuanced explorations of themes, symbolism, and literary devices. They have expressed a preference for evening reading sessions and have asked for book club-style discussion prompts to deepen their understanding of the texts.\n\nThe user has also shown interest in exploring the fantasy and science-fiction genres beyond their favorite authors. They have requested recommendations based on their preferences for complex world-building, compelling character arcs, and thought-provoking narratives. The assistant has introduced them to works by authors like Ursula K. Le Guin, Octavia E. Butler, and N.K. Jemisin, broadening their literary horizons.\n\nIn terms of format, the user has expressed a preference for both physical books and ebooks, often asking for comparisons between editions and discussions on the reading experience of each format. They have also inquired about audiobook options for their favorite titles, indicating a desire for flexibility in their reading experiences.\n\nThroughout their interactions, the user has maintained a curious and enthusiastic tone, eager to delve deeper into the worlds and themes of their favorite books. They have appreciated the assistant's ability to provide insightful analyses, thoughtful recommendations, and engaging discussions tailored to their literary interests.",
        "Buses": "The user, a young male student in his early 20s from the United Kingdom, frequently engages with the assistant to plan and book bus travel. As a student with a limited budget, he prefers affordable options like National Express and Megabus for his weekly commutes and occasional leisure trips.\n\nIn past interactions, the user has requested assistance in finding the most cost-effective bus routes and schedules, often favoring afternoon departures to accommodate his class schedule. He has a preference for window seats and has asked the assistant to prioritize these when available.\n\nOver time, the user has developed a habit of checking bus availability and prices well in advance, seeking the assistant's guidance on the best times to book for optimal savings. He has also inquired about student discounts and promotions offered by various bus companies.\n\nThe user appreciates the assistant's ability to provide clear, concise information about departure times, journey durations, and any potential delays or disruptions. He has occasionally requested real-time updates on bus locations and estimated arrival times, particularly when running late for a scheduled departure.\n\nIn addition to booking tickets, the user has sought recommendations for comfortable and affordable accommodation options near major bus stations for overnight stays during longer journeys. He has also inquired about luggage policies and the process of claiming lost or misplaced items.\n\nThe user's interactions with the assistant often reflect a casual and friendly tone, with a preference for straightforward language and a touch of humor. He values efficiency and convenience, appreciating the assistant's ability to streamline the bus travel planning process while considering his budget constraints and preferences.",
        "Calendar": "The user, a male student between 18-24 years old from the United Kingdom, frequently interacts with the calendar assistant to manage his busy schedule. As a university student, his primary focus is on coordinating study sessions and social gatherings with friends.\n\nIn the past, the user has requested the assistant to set up recurring weekly study group meetings, specifying the location, duration, and attendees. He often asks for reminders 30 minutes before these sessions, allowing him to prepare materials and arrive on time.\n\nAdditionally, the user enjoys recreational activities and frequently schedules outings with friends, such as movie nights, gaming sessions, or casual hangouts. He relies on the assistant to coordinate these events, providing details like the venue, time, and attendee list.\n\nOver time, the user has developed a preference for concise event summaries and clear, straightforward reminders. He appreciates when the assistant proactively suggests potential conflicts or overlaps in his schedule, allowing him to prioritize and make necessary adjustments.\n\nThe user's interactions with the assistant often involve last-minute changes or cancellations due to the dynamic nature of his social life and academic commitments. He values the assistant's ability to quickly update his calendar and notify relevant attendees about any modifications.\n\nAs a tech-savvy individual, the user has shown interest in integrating his calendar with other productivity apps and exploring features like shared calendars or event collaboration tools. He prefers a casual and friendly tone from the assistant, reflecting his youthful and social personality.",
        "Events": "The user, a male student aged 18-24 from the United Kingdom, frequently engages with the assistant to discover and plan attendance at various affordable events, particularly concerts, comedy shows, gaming conventions, and film screenings. His interactions often revolve around finding free or low-cost events under $50, preferably on weekends when he has more free time.\n\nIn the past, the user has requested recommendations for upcoming concerts by indie rock bands or EDM artists playing in his area. The assistant has provided personalized suggestions based on his music preferences and budget, sometimes even alerting him to free outdoor concerts or discounted student tickets.\n\nFor comedy shows, the user prefers general admission or standing tickets, allowing him to attend with a large group of friends. He has asked the assistant to find upcoming shows by popular comedians or improv troupes, often seeking events within walking distance of his university campus.\n\nGaming conventions and esports events are also of great interest to the user. He has inquired about upcoming gaming expos, tournaments, and release parties, particularly those offering free entry or discounted student passes. The assistant has helped him stay informed about the latest gaming news and events in his region.\n\nOver time, the user's interactions have evolved to include requests for film screenings of cult classics or independent movies at local theaters or pop-up venues. He appreciates the assistant's ability to provide comprehensive event details, including start times, locations, and any age restrictions or dress codes.\n\nThe user's tone is often casual and friendly, reflecting his youthful energy and enthusiasm for social events. He values the assistant's ability to understand his preferences for affordable, group-friendly events and provide timely updates on new event announcements or ticket sales.",
        "Finance": "The user, a young male student from the United Kingdom in his early 20s, has shown a growing interest in the finance domain, particularly in tracking stocks and news related to technology, consumer goods, and healthcare sectors. Despite his limited financial background, he has actively engaged with the virtual assistant to learn and stay informed about market trends.\n\nInitially, the user's interactions focused on seeking explanations of basic financial concepts, such as stock prices, market capitalization, and trading strategies. He often requested simplified definitions and analogies to grasp these topics better. Over time, his inquiries became more specific, asking for real-time stock updates on companies like Apple, Amazon, Netflix, and Tesla.\n\nThe user has a preference for consuming financial news through easily accessible channels like financial news channels, apps, and websites. He frequently asks the assistant to summarize key news articles or provide concise overviews of market events, especially those related to his preferred sectors. Additionally, he has shown interest in following financial blogs and podcasts recommended by the assistant, seeking diverse perspectives on investment strategies.\n\nAs his knowledge has grown, the user has started exploring more advanced topics, such as analyzing company earnings reports and understanding the impact of technological advancements on stock performance. He often requests visualizations and charts to better comprehend market trends and company valuations.\n\nThe user's interactions with the assistant have evolved from seeking basic information to engaging in more analytical discussions. He appreciates the assistant's ability to explain complex financial concepts in a relatable and easy-to-understand manner, often requesting examples or analogies to solidify his understanding.\n\nWhile the user's financial knowledge is still developing, he has expressed a desire to learn about investment strategies and potentially start building a portfolio. He values the assistant's objective and unbiased advice, frequently seeking recommendations on reliable resources and tools for beginners in the finance domain.",
        "Flights": "The user, a young male student in his early 20s from the United Kingdom, frequently interacts with the virtual assistant to search for and book affordable flights within Europe. As a budget-conscious traveler, he primarily focuses on low-cost airlines such as RyanAir, EasyJet, and Vueling.\n\nIn the past, the user has requested assistance in finding the cheapest non-stop or short layover flights for weekend getaways or short holidays. He prefers morning or afternoon departures and economy class seating, with a strong preference for aisle seats. The user often asks the assistant to compare prices across multiple airlines and dates to find the best deals.\n\nOver time, the user has developed a habit of providing feedback on his flight experiences, sharing insights on airline service, airport efficiency, and any delays or issues encountered. He has expressed frustration with hidden fees and has sought guidance on understanding airline policies and baggage allowances.\n\nThe user's interactions with the assistant have evolved to include requests for recommendations on budget-friendly accommodations and activities at his destinations. He has shown interest in exploring nearby cities or attractions that can be easily accessed from the airport.\n\nAdditionally, the user has inquired about the possibility of earning airline miles or loyalty rewards through frequent bookings, indicating a desire for long-term cost savings and perks. He appreciates clear and concise information, particularly when it comes to flight details, pricing breakdowns, and any potential disruptions or changes to his itinerary.",
        "Games": "The user, an 18-24 year old male student from the United Kingdom, is an avid gamer with a strong interest in action, RPG, survival, and sandbox games. Past interactions with the virtual assistant have primarily revolved around exploring new game titles, seeking recommendations, and staying updated on the latest releases across PC, PlayStation, and Nintendo Switch platforms.\n\nOne of the recurring themes in the user's interactions is their fondness for immersive, open-world games like The Witcher 3: Wild Hunt and Red Dead Redemption 2. They have frequently requested detailed walkthroughs, tips, and tricks to uncover hidden quests, easter eggs, and optimal character builds. Additionally, the user has sought guidance on obtaining and installing mods to enhance their gaming experience further.\n\nThe user's preference for online multiplayer games is evident in their frequent inquiries about popular multiplayer titles and requests for server recommendations. They have also expressed interest in joining gaming communities and forums to connect with like-minded players and stay informed about upcoming multiplayer events or tournaments.\n\nOver time, the user's interactions have evolved to include requests for game reviews, comparisons between different titles within the same genre, and recommendations for games with compelling narratives or intricate world-building. They have also shown an interest in exploring indie games and have asked the assistant to curate lists of underrated or lesser-known titles that align with their preferences.\n\nThe user appreciates a conversational and relatable tone from the assistant, often engaging in banter or sharing personal gaming experiences. They value concise yet informative responses, particularly when seeking specific information about game mechanics, system requirements, or troubleshooting tips. Additionally, the user has expressed a preference for visual aids, such as gameplay videos or screenshots, to complement the assistant's recommendations and explanations.",
        "Hotels": "Here is a realistic interaction summary for the specified user profile and domain:\n\nThe user, an 18-24 year old male university student from the United Kingdom, frequently interacts with the assistant to book hotel accommodations that align with his preferences and budget. He shows a strong affinity for boutique and budget hotel chains located in city centers or near university campuses.\n\nIn one instance, the user requested recommendations for a 3-star hotel in London with free parking, WiFi, and breakfast included, preferably within walking distance to nightlife hotspots. The assistant provided a curated list of options that met these criteria, and the user ultimately booked a double room at a trendy boutique hotel.\n\nOver time, the user's interactions have revealed a consistent pattern of prioritizing amenities like free WiFi for studying and gyms for working out. He often asks about hotel policies regarding late checkouts or guest allowances, hinting at a socially active lifestyle.  \n\nThe user appreciates when the assistant provides candid reviews of hotel cleanliness and service quality from other young travelers. He has provided positive feedback on the personalized hotel recommendations catered to his needs as a student on a limited budget.\n\nRecently, the user inquired about budget-friendly hotels near universities in Edinburgh for an upcoming trip with friends. He requested options with a lively bar scene and emphasized the importance of being centrally located for nightlife and sightseeing. The assistant compiled a list of 3-4 star hotels matching his preferences.\n\nThroughout the interactions, the user maintains a casual, friendly tone but can be quite direct in his requests. He values efficiency and has expressed frustration with long-winded responses, preferring concise information tailored to his needs as a young, budget-conscious traveler.",
        "Media": "The user, an 18-24 year old male student from the United Kingdom, frequently engages with the virtual assistant to explore and discover new media content, primarily in the realm of action, comedy, sci-fi, and adventure genres. Past interactions have revolved around seeking recommendations, accessing information about upcoming releases, and finding streaming options for movies and TV shows.\n\nOne recurring theme is the user's interest in the Marvel Cinematic Universe (MCU) and the work of actors like Tom Holland and Chris Hemsworth, as well as directors such as Taika Waititi and James Gunn. The user has often requested information about the latest MCU releases, such as Spider-Man: No Way Home and Thor: Ragnarok, and has sought out recommendations for similar superhero or action-packed movies and shows.\n\nInitially, the user's interactions focused on finding streaming platforms and rental options for specific titles, but over time, they began to rely more on the assistant's personalized recommendations. The user has expressed a preference for concise plot summaries, critic reviews, and trailers to help them decide on their next viewing experience.\n\nAs the user's tastes evolved, they began exploring more diverse genres, such as dark comedies and unconventional sci-fi, leading to recommendations like The Suicide Squad and other James Gunn projects. The user has also shown an interest in behind-the-scenes content, such as interviews with actors and directors, and has requested information about upcoming projects featuring their favorite artists.\n\nThroughout the interactions, the user has maintained a casual and conversational tone, often using slang and pop culture references. They have provided feedback on the assistant's recommendations, both positive and negative, helping to refine the personalization algorithms. The user has also expressed a preference for receiving notifications about new releases and updates related to their favorite franchises and artists.",
        "Messaging": "The user, a male student aged 18-24 from the United Kingdom, frequently engages with the virtual assistant for messaging-related tasks. His preferred messaging apps are WhatsApp, Snapchat, and Discord, which he primarily uses to communicate with friends and classmates.\n\nPast interactions often involve sending casual text messages to his contacts, with the user dictating the message content to the assistant. He appreciates the assistant's ability to understand and mimic his informal communication style, including the use of slang, abbreviations, and emojis.\n\nFor example, the user might ask the assistant to send a message to a friend on WhatsApp, saying something like \"Yo mate, wanna grab a pint later? \ud83c\udf7b\" or \"Yo, did you catch the game last night? It was wild! \ud83d\udd25\"\n\nThe user also frequently requests the assistant to share his location with specific contacts, especially when coordinating meetups or letting friends know his whereabouts. He values the convenience of being able to share his location without manually navigating the messaging app.\n\nOver time, the user has expressed interest in exploring additional messaging app features, such as creating group chats or setting up reminders for important conversations. He has also occasionally asked the assistant to suggest appropriate messaging etiquette or tone for communicating with classmates or professors.\n\nWhile the user primarily engages with the assistant for casual messaging purposes, he has shown an openness to using the assistant for more formal communication if needed, such as sending professional messages or coordinating group projects with classmates.\n\nOverall, the user's interactions with the assistant in the messaging domain reflect his preference for a casual, informal communication style and his reliance on popular messaging apps to stay connected with his social circle.",
        "Movies": "The user, an 18-24 year old male student from the United Kingdom, has a strong affinity for movies, particularly in the action, comedy, and science-fiction genres. Past interactions with the virtual assistant have primarily revolved around browsing and purchasing movie tickets for the latest blockbuster releases, with a preference for IMAX and standard theater experiences.\n\nOne recurring theme is the user's enthusiasm for movies featuring actors like Tom Holland, Chris Hemsworth, and Robert Downey Jr., as well as films directed by Taika Waititi. The user has frequently requested recommendations for upcoming movies starring these actors or directors, often seeking out early screenings or premiere dates.\n\nDuring school breaks and vacations, the user has a tendency to binge-watch movies, preferring late-night showings on weekends. In these instances, they have asked the assistant to curate a list of highly-rated films within their preferred genres, prioritizing double seats in the back row for an optimal viewing experience.\n\nOver time, the user has developed a habit of seeking the assistant's guidance in planning movie outings with friends, requesting group ticket purchases and coordinating transportation or dining options near the theater. They have also expressed interest in exploring independent or foreign films, occasionally venturing beyond their typical genre preferences.\n\nThe user's interactions are often casual and lighthearted, with a tendency to engage in banter or share humorous anecdotes related to their movie-going experiences. They appreciate concise summaries and clear recommendations, but also value the assistant's ability to provide in-depth analysis or trivia about their favorite films and actors.",
        "Music": "The user, an 18-24 year old male student from the United Kingdom, has a diverse taste in music, with a particular fondness for rock, punk, and hip-hop genres. Past interactions with the assistant have revolved around discovering new songs, albums, and artists within these genres, as well as creating and managing playlists for various activities.\n\nOne of the user's recurring requests has been for recommendations based on their favorite artists, such as Arctic Monkeys, Stormzy, Dave, Oasis, The Clash, and Blink-182. They have often asked the assistant to suggest similar artists or albums that align with their preferences for the raw energy of punk rock and the lyrical prowess of British hip-hop.\n\nThe user has also shown a keen interest in exploring new releases and staying up-to-date with the latest music trends. They frequently engage with the assistant's \"Release Radar\" and \"Discover Weekly\" playlists on platforms like Spotify and YouTube Music, seeking fresh sounds and potential new favorites.\n\nAdditionally, the user has requested the creation of workout playlists, blending their preferred genres to create high-energy mixes that can fuel their exercise routines. They have provided feedback on these playlists, indicating a preference for seamless transitions between tracks and a balanced mix of upbeat tempos.\n\nOver time, the user's interactions have evolved to include more specific requests, such as seeking out live performances, music videos, or behind-the-scenes content related to their favorite artists. They have also shown an interest in exploring the stories and influences behind iconic albums like \"Whatever People Say I Am, That's What I'm Not\" by Arctic Monkeys and \"Enema of the State\" by Blink-182.\n\nThroughout their interactions, the user has maintained a casual and enthusiastic tone, often expressing their excitement for new musical discoveries and sharing personal anecdotes or connections to certain songs or artists. They appreciate the assistant's ability to provide concise yet informative responses and have occasionally requested more in-depth analyses or trivia related to their music interests.",
        "Rental Cars": "The user, an 18-24 year old male student from the United Kingdom, frequently interacts with the virtual assistant to search for and reserve rental cars. His interactions often revolve around finding affordable compact or economy cars for short-term rentals, typically lasting 1-2 weeks.\n\nIn his initial interactions, the user expressed a preference for car rental companies like Zipcar and Enterprise, as well as car brands such as Volkswagen, Honda, and Toyota. He consistently requested additional features like GPS navigation and the option to add an additional driver, indicating a tendency to travel with friends or family.\n\nOver time, the user's interactions evolved to include more specific requests, such as searching for rentals within a certain price range or with a particular fuel type (gasoline). He also began to ask for recommendations on the most fuel-efficient models available, suggesting a growing interest in cost-saving and environmental considerations.\n\nThe user's tone in these interactions is often casual and straightforward, reflecting his age and familiarity with the rental process. He appreciates clear and concise responses from the assistant, particularly regarding pricing, availability, and rental policies.\n\nIn recent interactions, the user has shown an interest in exploring alternative transportation options, such as ride-sharing services or electric vehicles. He has inquired about the availability of these options through the rental companies he typically uses, indicating a potential shift in his preferences as he becomes more environmentally conscious or seeks more convenient transportation solutions.\n\nOverall, the user's interactions with the virtual assistant in the rental car domain have been consistent and focused on finding affordable, practical rental options that meet his short-term transportation needs as a student. His evolving preferences and openness to new alternatives suggest a willingness to adapt and explore more sustainable or convenient solutions as they become available.",
        "Restaurants": "The user, a university student aged 18-24 from the United Kingdom, frequently engages with the assistant to discover new vegetarian-friendly restaurants in his local area. Past interactions often involve requesting recommendations for casual Mexican, Thai, or Indian eateries with budget-friendly pricing and outdoor seating options.\n\nInitially, the user sought guidance on transitioning to a vegetarian diet, leading the assistant to suggest a variety of plant-based dishes and restaurants catering to this dietary preference. Over time, they developed a fondness for flavorful curries and spicy vegetarian fare, prompting requests for the best Indian and Thai spots in the city.\n\nThe user appreciates when the assistant provides detailed menu highlights, particularly for unique vegetarian offerings or creative meat-free twists on classic dishes. They have also inquired about restaurants with vegan options to accommodate friends or explore new culinary experiences.\n\nAs the user's culinary horizons expanded, they began seeking out more upscale vegetarian establishments for special occasions, while still maintaining a preference for casual, budget-friendly spots for everyday dining. The assistant has tailored recommendations accordingly, balancing affordability with ambiance and menu diversity.\n\nThroughout their interactions, the user has provided feedback on restaurant experiences, enabling the assistant to refine its understanding of their preferences further. They have expressed appreciation for concise summaries, highlighting key details like pricing, popular menu items, and any noteworthy vegetarian-friendly accommodations.\n\nThe user's tone is often casual and friendly, occasionally injecting humor or banter into the conversation. They value efficiency but also enjoy engaging in light-hearted discussions about food trends or sharing personal anecdotes related to their dining adventures.",
        "Services": "The user, a young male student in his early 20s from the United Kingdom, frequently interacts with the assistant to book various service appointments near his university campus. As a budget-conscious individual, he prioritizes affordable options within walking distance for monthly or one-off services.\n\nOne recurring interaction involves scheduling haircuts at local barbershops or salons that offer student discounts. The user often requests evening availability and prefers to review multiple options before making a selection based on price and convenience.\n\nFor medical needs, the user has sought assistance in finding dentists and general practitioners covered by his student health plan. He appreciates recommendations for providers with flexible evening hours and clear communication about appointment costs upfront.\n\nOver time, the user has developed a preference for service providers with online booking systems, as he finds it more convenient than making phone calls. He has also expressed interest in exploring budget-friendly options for occasional services like car maintenance or computer repairs.\n\nThe user's interactions are typically straightforward, focusing on obtaining practical information such as business hours, pricing, and location details. He values concise responses and dislikes excessive prompting or upselling attempts. While he has no specific gender preference for service providers, he has occasionally requested recommendations for businesses with positive reviews from fellow students.\n\nAs the user's needs evolve, he has shown an interest in exploring subscription-based services or bundled packages that could offer discounts for frequent appointments. Overall, his interactions reflect a pragmatic approach to finding convenient and affordable service options that fit his student lifestyle.",
        "Shopping": "The user, an 18-24 year old male student residing in the United Kingdom, frequently engages with the virtual assistant for shopping-related tasks, particularly in the electronics, books, and musical instruments categories. As a budget-conscious individual, he often seeks affordable yet well-reviewed products from environmentally conscious brands.\n\nIn the electronics domain, the user has requested recommendations for budget laptops suitable for university studies, prioritizing portability, battery life, and mid-range performance. He has also explored affordable audio equipment, such as headphones and speakers, valuing quality sound over brand recognition.\n\nFor books, the user has a keen interest in fiction, particularly fantasy and science fiction genres. He has asked for recommendations based on popular series and authors he enjoys, as well as suggestions for lesser-known but highly-rated titles within his preferred genres.\n\nWhen it comes to musical instruments, the user has shown a fondness for acoustic guitars and has inquired about beginner-friendly options with decent sound quality at an affordable price point. He has also expressed interest in learning to play the piano and has sought guidance on purchasing a suitable entry-level digital piano or keyboard.\n\nOver time, the user's interactions have evolved to include requests for product comparisons, particularly for electronics and musical instruments. He values detailed feature breakdowns, user reviews, and objective assessments of value for money. Additionally, he has shown an appreciation for the assistant's ability to provide unbiased recommendations based on his preferences and budget constraints.\n\nThe user's tone is often casual and friendly, and he appreciates clear and concise responses from the assistant. He has provided feedback on the helpfulness of recommendations and has occasionally sought clarification or additional details on specific product specifications or features.",
        "Sports": "The user, a young male student in his early 20s from the United Kingdom, has a deep passion for sports, particularly soccer, cricket, rock climbing, and skateboarding. Past interactions with the assistant have centered around accessing live scores, match schedules, and statistics for his favorite teams, Manchester United FC and the England National Cricket Team.\n\nOne recurring theme is the user's desire for real-time updates during live matches, often requesting the assistant to provide up-to-the-minute scores, commentary, and highlight clips. For instance, during crucial Manchester United games, the user would ask for regular score updates, key player stats, and video highlights of significant moments.\n\nOver time, the user's interests have expanded to include more niche sports like rock climbing and skateboarding. They have sought recommendations for upcoming competitions, athlete profiles, and training tips from the assistant. Additionally, they have requested information on local rock climbing gyms and skate parks, indicating a growing interest in actively participating in these sports.\n\nThe user's interactions are often spontaneous and casual, reflecting their youthful energy and enthusiasm. They appreciate concise, straightforward responses and have occasionally provided feedback on the assistant's ability to understand sports jargon and slang. The user has also expressed interest in personalized notifications for major sports events, especially those involving their favorite teams or athletes.\n\nAs their interests have evolved, the user has begun exploring sports-related podcasts and video channels recommended by the assistant. They have inquired about the best sources for in-depth analysis, behind-the-scenes content, and expert opinions on various sports topics.\n\nOverall, the user's interactions with the assistant revolve around staying up-to-date with the latest sports news, scores, and events, with a particular focus on soccer, cricket, rock climbing, and skateboarding. Their engagement reflects a dynamic and diverse range of sports interests, fueled by their youthful curiosity and passion for athletic pursuits.",
        "Train": "The user, a young male student in his early 20s from the United Kingdom, frequently engages with the assistant to book and manage train journeys within the country. As a budget-conscious traveler, he prefers standard class seating and values amenities like WiFi and power outlets during his trips.\n\nPast interactions often involve requesting train schedules and ticket prices for evening or morning travel times, with a preference for window seats. The user appreciates the assistant's ability to provide real-time updates on delays or cancellations, allowing him to plan accordingly.\n\nOver time, the user has developed a habit of asking for recommendations on the most cost-effective routes and times for specific journeys, relying on the assistant's knowledge of discounts and promotions. He has also inquired about the possibility of booking group tickets for occasional trips with friends.\n\nIn one instance, the user sought assistance in finding the quickest route from his university to his hometown, taking into account potential delays and transfer times. The assistant provided a comprehensive itinerary, including platform information and estimated travel duration.\n\nThe user values clear and concise communication, often providing feedback on the clarity of the assistant's responses. He has expressed a preference for receiving travel updates and reminders via text or email notifications, ensuring he stays informed throughout his journey.\n\nAs his travel needs evolve, the user has shown interest in exploring more flexible ticketing options, such as open returns or the ability to make changes to his bookings. He has also inquired about the possibility of booking international train journeys, indicating a potential expansion of his travel horizons in the future.",
        "Travel": "The user, an 18-24 year old male student from the United Kingdom, has a keen interest in exploring new destinations and seeking adventure through travel. Past interactions with the assistant have focused on planning trips that combine urban exploration with outdoor activities and natural landscapes.\n\nIn one instance, the user requested recommendations for a solo backpacking trip through the Scottish Highlands, seeking off-the-beaten-path hiking trails and opportunities for camping in remote areas. The assistant provided a curated itinerary that balanced scenic routes with visits to charming villages and historical sites.\n\nFor a summer trip with his partner, the user sought suggestions for a road trip through the Netherlands and Belgium, with a focus on experiencing local culture, cuisine, and nightlife in cities like Amsterdam and Brussels. The assistant tailored recommendations to include unique experiences like staying in a houseboat and attending local music festivals.\n\nOver time, the user has expressed a growing interest in longer, more immersive travel experiences. They have requested itineraries for 3-4 week trips that combine multiple destinations, such as a combination of city exploration in London and hiking in the Lake District or Snowdonia National Park.\n\nThe user values personalized recommendations that cater to their preferences for adventure, outdoor activities, and cultural immersion. They often seek off-the-beaten-path experiences and have shown an appreciation for sustainable and eco-friendly travel options. The assistant has provided guidance on budgeting, transportation options, and packing lists tailored to the user's preferred travel styles and durations.\n\nAs the user's travel aspirations have evolved, they have begun exploring options for more ambitious trips, such as multi-country backpacking adventures or long-term solo travel. The assistant has responded by providing resources on working holidays, volunteer opportunities, and tips for extended travel on a student budget."
    }
}