{
    "affinities": {
        "Alarm": {
            "Alarm Time Preference": "7:00 AM",
            "Alarm Sound Preference": "upbeat music",
            "Alarm Recurring Preference": "weekdays"
        },
        "Books": {
            "Genre": [
                "science-fiction",
                "fantasy",
                "thriller"
            ],
            "Favourite Authors": [
                "Isaac Asimov",
                "Frank Herbert",
                "J.R.R. Tolkien"
            ],
            "Favourite Books": [
                "Dune",
                "The Lord of the Rings",
                "I, Robot"
            ],
            "Favourite Book Series": [
                "The Foundation Series",
                "The Hitchhiker's Guide to the Galaxy"
            ],
            "Reading Format": [
                "physical",
                "ebook"
            ],
            "Reading Time Preference": [
                "evening"
            ],
            "Reading Frequency": "weekly"
        },
        "Buses": {
            "Preferred Bus Company": [
                "Austrian Federal Railways",
                "Flixbus"
            ],
            "Travel Frequency": [
                "weekly",
                "monthly"
            ],
            "Seat Preference": "window",
            "Departure Time Preference": [
                "morning",
                "afternoon"
            ]
        },
        "Calendar": {
            "Event Type Preference": [
                "social gatherings",
                "outdoor activities",
                "sports events"
            ],
            "Notification Preference": "30 minutes before",
            "Timezone": "UTC+1"
        },
        "Events": {
            "Event Type Preference": [
                "concerts",
                "festivals",
                "gaming conventions"
            ],
            "Price Range": [
                "under $50",
                "$50-$100"
            ],
            "Group Size Preference": "small group",
            "Seating Preference": [
                "general admission"
            ],
            "Days of Week Preference": "weekends"
        },
        "Finance": {
            "Preferred Sectors": [
                "technology",
                "consumer goods",
                "healthcare"
            ],
            "News Sources": [
                "financial websites",
                "company reports",
                "financial news channels",
                "financial apps"
            ],
            "Financial Company": [
                "Apple",
                "Google",
                "Amazon",
                "Tesla",
                "Netflix"
            ]
        },
        "Flights": {
            "Preferred Airline": [
                "Lufthansa",
                "Austrian Airlines"
            ],
            "Seat Class Preference": [
                "economy",
                "premium economy"
            ],
            "Layover Preference": [
                "non-stop",
                "short layover"
            ],
            "Seat Preference": "window",
            "Departure Time Preference": [
                "morning",
                "afternoon"
            ]
        },
        "Games": {
            "Preferred Game Genres": [
                "FPS",
                "action",
                "survival"
            ],
            "Gaming Platforms": [
                "PC",
                "PlayStation"
            ],
            "Multiplayer Preference": [
                "online multiplayer"
            ],
            "Gaming Frequency": [
                "2-3 times per week",
                "4-6 hours per session"
            ],
            "Preferred Game Name": [
                "Call of Duty: Modern Warfare",
                "Apex Legends",
                "Rust"
            ]
        },
        "Hotels": {
            "Hotel Chains Preference": [
                "Hilton",
                "boutique"
            ],
            "Amenity Preference": [
                "WiFi",
                "gym",
                "bar/lounge",
                "in-room safe"
            ],
            "Location Preference": [
                "city center",
                "near tourist attractions",
                "near cultural landmarks"
            ],
            "Star Rating Preference": [
                "4 star",
                "5 star"
            ],
            "Room Type Preference": [
                "double"
            ]
        },
        "Media": {
            "Preferred Genres": [
                "action",
                "sci-fi",
                "thriller"
            ],
            "Favourite Actors and Directors": [
                "Christian Bale",
                "Christopher Nolan",
                "Quentin Tarantino"
            ],
            "Favourite Media": [
                "Inception",
                "The Dark Knight",
                "Interstellar",
                "Pulp Fiction"
            ],
            "Viewing Platform Preference": [
                "Netflix",
                "Amazon Prime",
                "YouTube"
            ]
        },
        "Messaging": {
            "Preferred Messaging Apps": [
                "WhatsApp",
                "Telegram",
                "Discord"
            ],
            "Communication Style": "text",
            "Frequent Contact": [
                "friends",
                "coworkers"
            ],
            "Preferred Communication Style": "casual"
        },
        "Movies": {
            "Preferred Genres": [
                "action",
                "science-fiction",
                "comedy",
                "adventure"
            ],
            "Favorite Actors and Directors": [
                "Chris Hemsworth",
                "Tom Cruise",
                "Quentin Tarantino"
            ],
            "Theater Type Preference": [
                "IMAX",
                "standard"
            ],
            "Viewing Time Preference": [
                "evening",
                "weekends only"
            ],
            "Seat Type Preference": [
                "middle row",
                "reclining seats"
            ]
        },
        "Music": {
            "Preferred Genres": [
                "rock",
                "metal",
                "punk"
            ],
            "Favorite Artists": [
                "Rammstein",
                "System of a Down",
                "Linkin Park"
            ],
            "Favorite Bands": [
                "Metallica",
                "Slipknot",
                "Green Day"
            ],
            "Favorite Albums": [
                "Hybrid Theory by Linkin Park",
                "Toxicity by System of a Down",
                "Master of Puppets by Metallica"
            ],
            "Platform Preference": [
                "Spotify",
                "YouTube Music"
            ],
            "Preferred Audio Quality": "lossless",
            "Playlist Preference": [
                "high energy rock",
                "workout playlists",
                "rock anthems"
            ]
        },
        "Rental Cars": {
            "Car Type Preference": [
                "compact",
                "intermediate"
            ],
            "Preferred Rental Company": [
                "Sixt",
                "Europcar",
                "Hertz"
            ],
            "Preferred Car Brand": [
                "Volkswagen",
                "BMW",
                "Audi"
            ],
            "Rental Duration Preference": "1-2 weeks",
            "Additional Feature Preference": [
                "GPS",
                "navigation"
            ],
            "Preferred Fuel Type": "gasoline"
        },
        "Restaurants": {
            "Cuisine Preference": [
                "fusion",
                "Japanese",
                "Thai"
            ],
            "Dietary Restrictions": [],
            "Ambiance Preference": [
                "casual",
                "outdoor seating"
            ],
            "Price Range": [
                "moderate",
                "upscale"
            ]
        },
        "Services": {
            "Preferred Service Provider Types": "local",
            "Appointment Time Preference": [
                "evening"
            ],
            "Location Preference": [
                "near home",
                "easily accessible by public transport"
            ],
            "Service Frequency Preference": [
                "monthly",
                "one-off"
            ],
            "Service Provider Gender Preference": "no preference"
        },
        "Shopping": {
            "Preferred Product Category": [
                "electronics",
                "clothing",
                "sports"
            ],
            "Price Range Preference": "mid-range",
            "Brand Preference": [
                "Apple",
                "Adidas",
                "Sony"
            ]
        },
        "Sports": {
            "Favorite Sports": [
                "soccer",
                "tennis",
                "motorsports",
                "rock climbing"
            ],
            "Favorite Team": [
                "Red Bull Racing",
                "FC Red Bull Salzburg"
            ],
            "Viewing Preference": "live"
        },
        "Train": {
            "Preferred Train Class": "standard class",
            "Travel Time Preference": [
                "morning",
                "afternoon"
            ],
            "Amenity Preference": [
                "WiFi",
                "power outlet"
            ],
            "Preferred Seat Type": "aisle"
        },
        "Travel": {
            "Preferred Destination Types": [
                "city",
                "cultural",
                "historical",
                "urban exploration",
                "photography"
            ],
            "Duration Preference": [
                "3-7 days",
                "1-2 weeks"
            ],
            "Group Size Preference": [
                "solo",
                "couple"
            ],
            "Frequent Travel Destination": [
                "Berlin",
                "Prague",
                "Budapest"
            ],
            "Travel Season Preference": [
                "Spring",
                "Fall"
            ]
        }
    },
    "demographics": {
        "user_id": "user239",
        "age": "18-24 years old",
        "gender": "Male",
        "employment_status": "Working full-time",
        "education": "Completed Secondary School",
        "marital_status": "Never been married",
        "english_proficiency": "Fluent",
        "ethnicity": "N/A",
        "religion": "Non-religious",
        "birth_country": "Austria",
        "reside_country": "Austria"
    },
    "interests": {
        "Alarm": 1,
        "Books": 1,
        "Buses": 0,
        "Calendar": 1,
        "Events": 1,
        "Finance": 0,
        "Flights": 0,
        "Games": 1,
        "Hotels": 0,
        "Media": 1,
        "Messaging": 1,
        "Movies": 1,
        "Music": 1,
        "Rental Cars": 0,
        "Restaurants": 1,
        "Services": 0,
        "Shopping": 1,
        "Sports": 1,
        "Train": 0,
        "Travel": 1
    },
    "interactions": {
        "Alarm": "The user, a young working professional from Austria in his early 20s, frequently interacts with the assistant to manage his daily alarm settings. As a non-religious individual who completed secondary school, he values efficiency and convenience in his morning routine.\n\nPast interactions indicate a preference for setting a recurring weekday alarm at 7:00 AM, allowing him ample time to prepare for work. The user has expressed a liking for upbeat, energetic music as his alarm sound, often requesting recommendations for new, motivating tracks to start his day on a positive note.\n\nIn one instance, the user asked the assistant to set a one-time alarm for a Saturday morning, as he had plans to meet friends. On another occasion, he requested the assistant to temporarily disable his weekday alarms during a vacation period.\n\nOver time, the user has grown accustomed to the assistant's ability to understand and adapt to his preferences. He appreciates the assistant's proactive reminders to set alarms before important events or appointments, as well as its suggestions for gradually increasing the alarm volume for a gentler wake-up experience.\n\nThe user's interactions with the assistant are typically straightforward and to-the-point, reflecting his fluency in English and his practical approach to task management. He values the assistant's clear and concise responses, particularly when confirming or modifying alarm settings.\n\nWhile the alarm domain is relatively focused, the user has occasionally explored additional features, such as setting reminders or integrating with his calendar. However, his primary use case remains centered around efficiently managing his morning alarm routine, ensuring a consistent and reliable start to his workdays.",
        "Books": "The user, a young working professional from Austria in his early 20s, is an avid reader with a particular passion for science fiction, fantasy, and thriller genres. Past interactions with the virtual assistant have centered around exploring and discussing books within these preferred genres.\n\nOne recurring theme is the user's deep appreciation for the works of authors like Isaac Asimov, Frank Herbert, and J.R.R. Tolkien. They have frequently requested summaries, analyses, and recommendations related to seminal works such as \"Dune,\" \"The Lord of the Rings,\" and \"I, Robot.\" The user has also shown a keen interest in exploring the broader universes and series surrounding these books, often seeking insights into the deeper themes, character development, and world-building.\n\nOver time, the user has developed a preference for physical books but has also embraced ebooks for convenience. They typically engage with the assistant in the evenings, seeking book recommendations or discussing the latest releases within their preferred genres. The user values in-depth discussions and analyses, often probing the assistant for its perspective on the philosophical or scientific concepts explored in the books.\n\nIn addition to the classics, the user has shown a growing interest in exploring lesser-known or emerging authors within the science fiction and fantasy realms. They have requested recommendations for thought-provoking, imaginative works that challenge conventional narratives or offer unique perspectives on societal issues.\n\nThe user's interactions with the assistant have evolved from seeking basic book summaries and recommendations to more nuanced discussions on character arcs, plot twists, and the broader cultural impact of certain works. They have also expressed interest in participating in virtual book clubs or discussion forums facilitated by the assistant, where they can engage with fellow enthusiasts and share their insights.\n\nThroughout their interactions, the user has maintained a respectful and inquisitive tone, valuing the assistant's ability to provide well-researched and thought-provoking responses. They appreciate recommendations that align with their preferences while also introducing them to new and exciting literary worlds.",
        "Buses": "The user, a young working professional in his early 20s from Austria, frequently utilizes the virtual assistant to manage his bus travel needs. With a preference for Austrian Federal Railways and Flixbus, he often requests information on routes, schedules, and ticket prices for both weekly and monthly trips.\n\nIn one instance, the user asked the assistant to find the most convenient morning bus from Vienna to Salzburg, preferably with a window seat. The assistant provided multiple options, including departure times, durations, and ticket costs, allowing the user to make an informed decision.\n\nOver time, the user has developed a habit of checking bus availability and purchasing tickets well in advance, often asking the assistant to set reminders for popular routes during peak travel seasons. He appreciates the assistant's ability to provide real-time updates on delays or cancellations, ensuring he can adjust his plans accordingly.\n\nThe user has also expressed interest in exploring more eco-friendly transportation options, leading the assistant to suggest bus companies with a strong sustainability focus. Additionally, he has requested recommendations for scenic routes and pit stops, indicating a desire to enhance his travel experiences.\n\nWhile the user's interactions are primarily focused on practical travel needs, he has occasionally sought the assistant's guidance on local attractions and cultural events near his destinations. This suggests a potential interest in combining his bus trips with leisure activities or exploring new cities during his travels.\n\nOverall, the user values efficiency, convenience, and reliability when it comes to bus travel. He appreciates the assistant's ability to provide clear, concise information and enjoys the personalized recommendations tailored to his preferences and travel patterns.",
        "Calendar": "The user, a young working professional in his early 20s from Austria, frequently interacts with the calendar assistant to manage his busy social and recreational schedules. As an avid sports enthusiast, he often requests the addition of local soccer matches, hiking trips, and outdoor adventure activities to his calendar.\n\nIn the past, the user has asked the assistant to set reminders for weekly kickboxing sessions with friends and monthly rock climbing meetups. He appreciates receiving notifications 30 minutes before each event, allowing him ample time to prepare and commute.\n\nOccasionally, the user seeks recommendations for nearby social gatherings or festivals, expressing interest in spontaneous weekend plans. The assistant has provided suggestions for local music festivals, food truck events, and outdoor movie screenings, which the user has enthusiastically added to his calendar.\n\nOver time, the user has developed a preference for concise event descriptions and has requested the assistant to include relevant details such as location, duration, and weather forecasts for outdoor activities. He values efficiency and has occasionally asked the assistant to suggest optimal routes or transportation options to minimize travel time.\n\nThe user's interactions often reflect his active lifestyle and social nature. He has expressed a desire for the assistant to integrate with fitness tracking apps, allowing him to seamlessly schedule workout sessions based on his activity levels. Additionally, he has inquired about sharing calendar access with close friends, facilitating coordinated planning for group outings and events.",
        "Events": "The user, a young working professional in his early 20s from Austria, frequently engages with the assistant to explore and attend local events, particularly concerts, festivals, and gaming conventions. Past interactions have revolved around finding affordable options within the $50-$100 price range, suitable for small groups on weekends.\n\nOne recurring theme has been the user's interest in discovering lesser-known indie music acts and underground events. They often ask for recommendations on up-and-coming artists performing in intimate venues or unique festival experiences in the region. The assistant has curated personalized lists of general admission shows aligning with the user's eclectic taste in rock, electronic, and alternative genres.\n\nOver time, the user has developed a preference for immersive, multi-day events like gaming conventions or music festivals. They have requested detailed schedules and tips for navigating large-scale events efficiently, maximizing their experience within a limited budget. The assistant has provided logistical guidance, such as transportation options, food recommendations, and strategies for securing early entry or prime viewing spots.\n\nThe user values the assistant's ability to filter events based on their specific criteria, such as price range, group size, and genre preferences. They appreciate concise event summaries with essential details like venue, date, and ticket availability. Additionally, the user has sought the assistant's help in coordinating with friends, sharing event details, and managing group purchases.\n\nAs their interests have evolved, the user has begun exploring events beyond their local area, occasionally requesting recommendations for weekend getaways or road trips to attend unique festivals or concerts in neighboring regions. They have also expressed interest in learning about volunteer opportunities at larger events, aligning with their desire for immersive experiences.",
        "Finance": "The user is a young working professional in their early 20s from Austria with a keen interest in finance and investing. Despite their age, they have shown a mature understanding of the stock market and a desire to stay informed about the latest developments in the technology, consumer goods, and healthcare sectors.\n\nPast interactions with the assistant have primarily revolved around tracking stock prices and news updates for major companies like Apple, Google, Amazon, Tesla, and Netflix. The user frequently requests real-time stock quotes, company earnings reports, and financial analyses from reputable websites and news channels.\n\nOne recurring theme is the user's curiosity about emerging technologies and their potential impact on the market. They often ask for insights into new product launches, technological advancements, and industry trends, particularly in the tech and consumer goods sectors. For instance, they might inquire about the implications of Apple's latest iPhone release or Tesla's advancements in electric vehicle technology.\n\nThe user values concise and visually appealing presentations of financial data, such as interactive charts and graphs that allow them to easily compare stock performances and identify patterns. They have expressed a preference for receiving news updates and market analyses in a digestible format, with clear summaries and actionable insights.\n\nOver time, the user has shown an increasing interest in exploring investment opportunities and diversifying their portfolio. They have requested guidance on evaluating potential stocks, understanding financial ratios, and identifying promising companies in sectors like healthcare. The assistant has provided educational resources and recommendations for reputable financial apps and tools to aid in their investment journey.\n\nAdditionally, the user has demonstrated a desire for personalized alerts and notifications, such as stock price triggers or news alerts for companies in their watchlist. They appreciate the assistant's ability to tailor the information to their specific interests and preferences, ensuring they stay up-to-date with the latest developments that could impact their investment decisions.\n\nOverall, the user's interactions with the assistant reflect a curious and analytical mindset, coupled with a willingness to learn and adapt as their financial knowledge and interests evolve. They value clear, concise, and visually appealing presentations of financial data, and seek guidance in navigating the complexities of the stock market.",
        "Flights": "The user, a young working professional in his early 20s from Austria, frequently interacts with the assistant to search for and book flights, primarily with Lufthansa and Austrian Airlines. He prefers non-stop or short layover flights in economy or premium economy class, with a strong preference for window seats.\n\nIn one instance, the user requested assistance in finding the most affordable non-stop flight from Vienna to Barcelona for a weekend getaway. The assistant provided several options, and the user ultimately booked a morning departure with Lufthansa's premium economy class, expressing satisfaction with the legroom and meal service.\n\nOn another occasion, the user sought help in coordinating a multi-city trip to Italy, with stops in Rome, Florence, and Venice. The assistant recommended an efficient itinerary with short layovers, and the user booked afternoon flights with Austrian Airlines, requesting window seats for better views during the journey.\n\nOver time, the user has developed a preference for receiving flight updates and gate information directly from the assistant, often asking for reminders and notifications closer to the travel dates. He also appreciates the assistant's ability to quickly retrieve and compare flight options based on his preferences, allowing him to make informed decisions.\n\nThe user's interactions are typically straightforward and focused on finding the most convenient and cost-effective flight options. He values clear and concise responses, with a particular interest in any available discounts or promotions. While he rarely engages in small talk, he occasionally expresses excitement about upcoming trips or shares brief anecdotes from previous travel experiences.",
        "Games": "The user, a young working professional in their early 20s from Austria, is an avid gamer with a strong preference for first-person shooter (FPS), action, and survival games. Past interactions with the virtual assistant have primarily revolved around finding and purchasing the latest releases in these genres, as well as seeking recommendations for similar titles.\n\nOne recurring theme is the user's interest in online multiplayer games, particularly the Call of Duty: Modern Warfare and Apex Legends franchises. They frequently ask for updates on upcoming multiplayer events, new maps, and gameplay strategies from the gaming community. The assistant has provided detailed information on limited-time game modes, as well as tips for improving team coordination and communication.\n\nThe user also enjoys survival games like Rust and has requested guidance on optimizing their in-game base defenses and resource management strategies. They appreciate the assistant's ability to summarize community forums and provide concise overviews of gameplay mechanics and updates.\n\nOver time, the user's engagement with the assistant has evolved to include requests for early access to game demos and beta versions, as well as inquiries about pre-order bonuses and exclusive content. They have also expressed interest in exploring virtual reality (VR) gaming experiences and have sought recommendations for compatible hardware and software.\n\nThe user values the assistant's ability to provide objective reviews and comparisons between games and gaming platforms, particularly when considering new purchases. They appreciate a direct and informative communication style, with a focus on practical details and actionable insights.\n\nAdditionally, the user has occasionally asked for recommendations on gaming-related merchandise, such as collectibles or apparel, indicating a broader interest in the gaming culture beyond just playing the games themselves.",
        "Hotels": "The user, a young professional in their early 20s from Austria, frequently interacts with the assistant to book hotel accommodations for both business and leisure trips. They have a strong preference for well-established hotel chains like Hilton and boutique hotels located in city centers or near major tourist attractions and cultural landmarks.\n\nDuring past interactions, the user has consistently requested 4- or 5-star hotels with amenities such as high-speed WiFi, a gym, a bar or lounge, and an in-room safe. They often inquire about room availability and rates for double occupancy rooms, suggesting they may travel with a partner or friend.\n\nThe user values efficiency and tends to provide clear criteria for their hotel searches, such as specific dates, location preferences, and desired amenities. They appreciate concise summaries of hotel options that highlight key features and allow for easy comparison.\n\nOver time, the user has demonstrated an interest in exploring local culture and cuisine during their stays. They have requested recommendations for highly-rated restaurants and cultural events near their hotel choices.\n\nAdditionally, the user has expressed a preference for hotels that offer loyalty programs or rewards, indicating a desire for value and potential discounts for frequent stays. They have also inquired about the possibility of early check-in or late check-out options, suggesting a need for flexibility in their travel plans.\n\nThe user's interactions are typically straightforward and professional, reflecting their working status. They appreciate prompt responses and clear communication from the assistant, particularly when confirming reservation details or addressing any special requests or concerns.",
        "Media": "The user, a young working professional in their early 20s from Austria, frequently engages with the virtual assistant to explore and discover new movies and TV shows across various streaming platforms. With a strong affinity for action, sci-fi, and thriller genres, their interactions often revolve around seeking recommendations, accessing trailers, and finding where to watch their favorite titles.\n\nOne recurring theme is the user's admiration for the works of Christopher Nolan and Quentin Tarantino, two directors known for their unique storytelling styles and mind-bending narratives. They have repeatedly asked the assistant for in-depth analyses and trivia about films like Inception, The Dark Knight, and Pulp Fiction, seeking to gain a deeper understanding of the creative processes behind these acclaimed works.\n\nOver time, the user has developed a preference for personalized recommendations based on their viewing history and ratings. They often request curated lists of lesser-known movies or TV shows that align with their taste for thought-provoking, action-packed narratives. The assistant has learned to suggest titles that feature actors like Christian Bale, known for his intense and transformative performances.\n\nIn addition to recommendations, the user frequently seeks information on where to stream or rent specific titles, particularly those not available on their preferred platforms, Netflix and Amazon Prime. They have expressed interest in exploring alternative platforms like YouTube for independent or niche content, and have occasionally requested guidance on navigating these platforms effectively.\n\nThe user's interactions with the assistant often involve a mix of casual conversation and specific queries. They appreciate a friendly and knowledgeable tone, but also value concise and accurate information. As their trust in the assistant's recommendations has grown, they have become more open to exploring new genres or directors, while still maintaining a preference for the familiar themes and styles they enjoy.\n\nOverall, the user's engagement with the assistant reflects a passion for immersive storytelling and a desire to stay up-to-date with the latest releases and trends in the world of movies and TV shows, particularly within the action, sci-fi, and thriller genres.",
        "Messaging": "The user, a young Austrian male in his early 20s, frequently engages with messaging apps like WhatsApp, Telegram, and Discord to stay connected with friends and coworkers. His interactions with the virtual assistant often revolve around sending text messages or sharing locations through these platforms.\n\nOne recurring theme is coordinating social plans with friends. The user would ask the assistant to draft casual text messages proposing hangout ideas, such as grabbing drinks or catching a movie. He appreciates the assistant's ability to capture his relaxed, conversational tone while ensuring the messages are concise and clear.\n\nFor work-related communication, the user relies on the assistant to compose professional yet friendly messages to colleagues on Discord or Telegram. These messages might involve coordinating project deadlines, sharing updates, or scheduling team meetings. The user values the assistant's ability to strike the right balance between formality and approachability in these contexts.\n\nOver time, the user has also requested assistance with sharing his location through messaging apps, particularly when meeting up with friends in unfamiliar areas or providing his whereabouts to family members. He appreciates the assistant's ability to seamlessly integrate location sharing into the messaging flow, making the process effortless.\n\nAdditionally, the user has explored using the assistant to manage group chats on various platforms. This includes tasks like creating new group conversations, adding or removing participants, and setting appropriate group names or descriptions. The user values the assistant's ability to streamline these administrative tasks while adhering to the platform's specific features and conventions.\n\nThroughout these interactions, the user's communication style remains casual and relaxed, reflecting his age and social circles. He appreciates the assistant's ability to adapt to his preferred tone and messaging etiquette, ensuring a natural and seamless experience across different platforms and contexts.",
        "Movies": "The user, a young working professional from Austria in his early 20s, has a strong affinity for movies, particularly in the action, science-fiction, comedy, and adventure genres. Past interactions with the assistant have revolved around exploring movie listings, purchasing tickets, and seeking recommendations tailored to his preferences.\n\nOne recurring theme has been the user's interest in blockbuster films featuring his favorite actors, such as Chris Hemsworth and Tom Cruise. He frequently asks the assistant to provide updates on upcoming releases starring these actors, often inquiring about showtimes and ticket availability for IMAX or standard theaters with reclining seats in the middle rows.\n\nThe user has a particular fondness for the works of director Quentin Tarantino and has requested the assistant to notify him whenever a new Tarantino film is released. He values the assistant's ability to provide in-depth plot summaries, critical reviews, and trivia related to these highly anticipated movies.\n\nOver time, the user has expressed a desire to explore lesser-known independent films and has sought the assistant's guidance in discovering hidden gems within his preferred genres. He appreciates personalized recommendations based on his viewing history and has shown interest in attending film festivals or special screenings.\n\nThe user's interactions often occur during evenings and weekends, reflecting his preference for viewing movies during these times. He has occasionally asked the assistant to suggest nearby restaurants or bars for pre-movie or post-movie gatherings with friends.\n\nIn terms of interaction style, the user prefers a conversational tone with a touch of humor. He values concise yet informative responses and appreciates when the assistant provides additional context or behind-the-scenes details about the movies he's interested in.",
        "Music": "The user, a young Austrian male in his early 20s working full-time, has a deep passion for rock, metal, and punk music. Past interactions with the assistant have primarily revolved around discovering new songs, albums, and artists within these genres, as well as creating and curating high-energy playlists for various activities.\n\nOne recurring theme has been the user's affinity for iconic rock and metal bands like Metallica, Slipknot, and Green Day. They frequently request recommendations for albums and songs similar to classics such as \"Master of Puppets\" by Metallica or \"American Idiot\" by Green Day. The user has also expressed a particular fondness for the albums \"Hybrid Theory\" by Linkin Park and \"Toxicity\" by System of a Down, often asking for related artists or deep cuts from these albums.\n\nOver time, the user has developed a preference for lossless audio quality, preferring to stream music on platforms like Spotify or YouTube Music. They have requested assistance in creating workout playlists featuring high-energy rock and metal tracks, as well as curated playlists of rock anthems for various occasions.\n\nThe user's interactions often involve seeking out new music recommendations based on their existing preferences, with a particular emphasis on discovering lesser-known or underground bands within the rock, metal, and punk genres. They have also shown interest in attending live concerts and have asked for information about upcoming tours and events featuring their favorite artists.\n\nThroughout the interactions, the user has maintained a direct and straightforward communication style, often providing concise feedback on recommendations and expressing a preference for succinct, to-the-point responses. They have also demonstrated a willingness to explore new subgenres and styles within the broader rock and metal umbrella, as long as the recommendations align with their overall musical tastes.",
        "Rental Cars": "The user, a young working professional in his early 20s from Austria, frequently interacts with the assistant to book rental cars for short trips around Europe. He prefers compact or intermediate-sized vehicles from reputable brands like Volkswagen, BMW, and Audi, often renting from companies like Sixt, Europcar, and Hertz.\n\nIn past interactions, the user has requested rental car options for 1-2 week trips to nearby countries, specifying his preference for gasoline-powered vehicles equipped with GPS navigation systems. He values efficiency and tends to book rentals close to his travel dates, occasionally seeking last-minute deals.\n\nThe user appreciates clear comparisons of pricing and vehicle features across different rental companies. He has expressed a preference for straightforward communication and dislikes excessive upselling or promotional offers. Over time, he has begun to inquire about long-term rental options for extended stays or potential relocation within Europe.\n\nInteractions often involve the user providing specific travel dates and locations, then reviewing and selecting from a curated list of rental options that align with his preferences. He occasionally requests additional details on fuel efficiency, mileage limits, or insurance coverage before finalizing his reservation.\n\nThe user's interactions reflect a practical and no-frills approach to car rentals, prioritizing affordability, convenience, and reputable brands. He values the assistant's ability to quickly present relevant options tailored to his needs, without overwhelming him with excessive choices or unnecessary extras.",
        "Restaurants": "The user, a young Austrian professional in his early 20s, frequently engages with the assistant to discover new dining experiences and make restaurant reservations. With a penchant for fusion, Japanese, and Thai cuisines, he often seeks recommendations for trendy eateries offering unique flavor combinations and innovative dishes.\n\nIn one interaction, the user requested a list of casual fusion restaurants with outdoor seating in Vienna's city center, preferably within a moderate price range. The assistant provided a curated selection, highlighting spots like Chez Dang, known for its Vietnamese-French fusion fare and lively patio ambiance.\n\nOn another occasion, the user sought an upscale Japanese restaurant suitable for celebrating a promotion with colleagues. The assistant suggested Shiki, a Michelin-starred establishment renowned for its omakase tasting menu and impeccable service.\n\nOver time, the user has grown more adventurous, expressing interest in exploring lesser-known Thai eateries that offer authentic regional specialties. The assistant has responded by recommending hidden gems like Siam Imbiss, a no-frills spot praised for its flavorful curries and street food-inspired dishes.\n\nThe user appreciates the assistant's ability to filter recommendations based on his dietary preferences, as he occasionally requests vegan or vegetarian options. He values concise summaries that highlight each restaurant's signature dishes, ambiance, and notable accolades or reviews.\n\nAdditionally, the user has begun inquiring about private dining spaces or event venues suitable for hosting small gatherings or celebrations with friends and family. The assistant has provided tailored suggestions, such as the intimate dining room at Mochi or the charming courtyard at Kussmaul, both offering a memorable atmosphere for special occasions.",
        "Services": "The user, a young working professional in his early 20s from Austria, frequently utilizes the assistant to book appointments with local service providers for various needs. Convenience and accessibility are key priorities, with a preference for businesses located near his home or easily reachable by public transportation.\n\nFor routine services like haircuts or dental cleanings, the user tends to schedule monthly appointments during evening hours to accommodate his work schedule. In these instances, he often requests a list of highly-rated providers within a specific radius, along with their availability and pricing details. The assistant has learned to prioritize recommendations based on proximity and positive reviews.\n\nWhen seeking one-off services, such as medical consultations or home repairs, the user values detailed information about the provider's expertise, certifications, and customer ratings. He has occasionally asked for comparisons between multiple providers to make an informed decision.\n\nOver time, the user has developed a preference for certain businesses and has requested the assistant to prioritize those when available. However, he remains open to trying new providers if they receive exceptional reviews or offer promotions.\n\nThe user's interactions are typically straightforward and to-the-point, with a focus on efficiency and convenience. He appreciates clear communication regarding appointment details, pricing, and any necessary preparations or requirements. While he has no specific gender preference for service providers, he has occasionally inquired about the availability of multilingual staff to accommodate his fluency in English.\n\nOverall, the user's engagement with the assistant revolves around streamlining the process of finding and booking reliable local services that fit his schedule and preferences, with a emphasis on proximity, positive reviews, and transparent pricing information.",
        "Shopping": "The user, a young working professional in his early 20s from Austria, frequently engages with the virtual assistant for shopping-related tasks, particularly in the electronics, clothing, and sports categories. Past interactions reveal a strong preference for mid-range products from popular brands like Apple, Adidas, and Sony.\n\nOne recurring theme is the user's interest in staying up-to-date with the latest gadgets and technology releases. They often ask the assistant to provide detailed comparisons between newly launched smartphones, laptops, or gaming consoles, seeking recommendations tailored to their budget and needs. The user appreciates the assistant's ability to highlight key features, technical specifications, and user reviews, enabling informed purchase decisions.\n\nIn the clothing domain, the user frequently requests suggestions for trendy and versatile outfits suitable for various occasions, such as work, casual outings, or sports activities. They value the assistant's ability to curate personalized recommendations based on their style preferences, body type, and budget constraints. The user has shown a particular fondness for Adidas sportswear and often seeks the assistant's guidance on upcoming product launches or limited-edition collections.\n\nOver time, the user has developed a habit of consulting the assistant before making significant purchases, valuing its objective analysis and ability to surface relevant product details, user reviews, and pricing comparisons across multiple retailers. They appreciate the assistant's concise and straightforward communication style, with a focus on providing actionable information and recommendations.\n\nAs their trust in the assistant's capabilities grew, the user began exploring new product categories, such as sports equipment and outdoor gear. They sought recommendations for durable and high-quality items suitable for hiking, camping, or other outdoor activities, demonstrating an interest in an active lifestyle.\n\nThe user's interactions with the assistant often involve specific queries about product availability, delivery timelines, and return policies, reflecting their desire for a seamless and hassle-free shopping experience. They have also expressed interest in receiving personalized alerts or notifications about upcoming sales, discounts, or restocks on their preferred products and brands.",
        "Sports": "The user, a young working professional from Austria, is an avid sports enthusiast with a particular passion for soccer, tennis, motorsports, and rock climbing. Past interactions with the assistant have revolved around accessing live scores, match schedules, and statistics for their favorite teams and athletes.\n\nSoccer is a recurring theme, with the user frequently requesting updates on FC Red Bull Salzburg's matches, player performances, and league standings. They have also shown keen interest in following major international tournaments like the UEFA Champions League and the FIFA World Cup.\n\nIn the realm of motorsports, the user closely tracks the Formula One season, eagerly seeking race results, driver standings, and news updates from the Red Bull Racing team. They have requested detailed analyses of race strategies, pit stop timings, and team tactics, demonstrating a deep understanding of the sport.\n\nTennis is another area of interest, with the user following Grand Slam tournaments and the performances of top-ranked players. They have asked for head-to-head statistics, historical records, and insights into players' strengths and weaknesses on different surfaces.\n\nRock climbing, while a niche interest, has also been a topic of discussion. The user has inquired about upcoming competitions, sought advice on training routines, and explored the latest gear and equipment recommendations.\n\nOver time, the user has developed a preference for live updates and real-time notifications, particularly during major sporting events. They appreciate concise, data-driven summaries and have expressed interest in visualizations and interactive dashboards to track their favorite teams and athletes more effectively.\n\nThe user's interactions often reflect a competitive spirit and a desire for in-depth analysis. They value objective insights and expert commentary, frequently requesting opinions from renowned coaches, analysts, and former athletes. Additionally, they have shown an interest in exploring emerging technologies, such as virtual reality and augmented reality, that enhance the sports viewing experience.",
        "Train": "The user, a young working professional from Austria in his early 20s, frequently uses the virtual assistant to book and manage train journeys within the country. With a preference for standard class travel during morning and afternoon hours, the user values convenience and amenities like WiFi and power outlets when planning train trips.\n\nPast interactions often involve requesting train schedules and ticket availability for specific routes, with a consistent preference for aisle seats. The user appreciates the assistant's ability to provide real-time updates on delays or cancellations, as well as recommendations for alternative routes or departure times when necessary.\n\nOver time, the user has expressed interest in exploring more cost-effective options, such as discounted fares or loyalty programs, while maintaining their preferred amenities and travel times. They have also requested information on train station facilities, such as luggage storage or waiting areas, to better plan their journeys.\n\nThe user's interactions are typically straightforward and to-the-point, reflecting their practical approach to travel. They value clear and concise information, with a focus on efficiency and minimizing disruptions. While open to suggestions, the user ultimately prefers to make their own decisions based on the provided options.\n\nAs a fluent English speaker, the user appreciates clear communication and has occasionally sought clarification on technical terms or policies related to train travel. They have expressed a preference for a friendly yet professional tone from the assistant, valuing a balance between personalization and objectivity.",
        "Travel": "The user, a young working professional from Austria in their early 20s, has a keen interest in exploring new cities and immersing themselves in different cultures. Past interactions with the assistant have focused on planning short trips to nearby European destinations like Berlin, Prague, and Budapest.\n\nThe user often seeks recommendations for off-the-beaten-path attractions and hidden gems in these cities, particularly those suited for urban exploration and photography. They have requested curated itineraries for solo trips, as well as suggestions for couples' getaways with their significant other.\n\nIn one instance, the user asked for a 5-day itinerary in Berlin, emphasizing lesser-known street art locations, unique cafes, and opportunities to capture the city's vibrant nightlife through photography. For a trip to Prague, they requested recommendations for historical walking tours and tips on navigating the city's intricate architecture.\n\nThe user values concise yet comprehensive recommendations tailored to their preferences for Spring and Fall travel. They appreciate suggestions that balance cultural immersion with opportunities for urban exploration and photography. Over time, they have expressed interest in extending their trips to 1-2 weeks, allowing for a more in-depth exploration of each destination.\n\nThe user often provides feedback on the recommendations, sharing their experiences and highlighting particularly memorable moments. They have a preference for a friendly and casual tone, and appreciate personalized touches, such as reminders about local customs or phrases in the destination's language.\n\nAs their travel experiences grow, the user has begun seeking recommendations for more off-the-beaten-path destinations within Europe, while still prioritizing cities rich in culture, history, and urban character. They have also shown interest in learning about sustainable travel practices and eco-friendly accommodations."
    }
}